setup.py
initclass/__init__.py.py
initclass.egg-info/PKG-INFO
initclass.egg-info/SOURCES.txt
initclass.egg-info/dependency_links.txt
initclass.egg-info/not-zip-safe
initclass.egg-info/top_level.txt